stablefused/__init__.py
stablefused/diffusion/__init__.py
stablefused/diffusion/base_diffusion.py
stablefused/diffusion/image_to_image_diffusion.py
stablefused/diffusion/inpaint_diffusion.py
stablefused/diffusion/latent_walk_diffusion.py
stablefused/diffusion/text_to_image_diffusion.py
stablefused/diffusion/text_to_video_diffusion.py
stablefused/typing/__init__.py
stablefused/typing/enums.py
stablefused/typing/type_hints.py
stablefused/utils/__init__.py
stablefused/utils/diffusion_utils.py
stablefused/utils/image_utils.py
stablefused/utils/model_cache.py
stablefused-0.2.0.dist-info/LICENSE
stablefused-0.2.0.dist-info/METADATA
stablefused-0.2.0.dist-info/WHEEL
stablefused-0.2.0.dist-info/top_level.txt
stablefused-0.2.0.dist-info/RECORD
