Metadata-Version: 2.1
Name: stablefused
Version: 0.2.0
Summary: StableFused is a toy library to experiment with Stable Diffusion inspired by 🤗 diffusers and various other sources!
Home-page: https://github.com/a-r-r-o-w/stablefused/
Author: Aryan V S
Author-email: contact.aryanvs+stablefused@gmail.com
License: MIT
Classifier: Development Status :: 1 - Planning
Classifier: Intended Audience :: Science/Research
Classifier: Intended Audience :: Developers
Classifier: Intended Audience :: Education
Classifier: Programming Language :: Python :: 3
Classifier: Programming Language :: Python :: 3.8
Classifier: Programming Language :: Python :: 3.9
Classifier: Programming Language :: Python :: 3.10
Classifier: Operating System :: Microsoft :: Windows
Classifier: Operating System :: Unix
Classifier: License :: OSI Approved :: MIT License
Classifier: Topic :: Scientific/Engineering :: Artificial Intelligence
Requires-Python: >=3.8.0
License-File: LICENSE
Requires-Dist: accelerate ==0.21.0
Requires-Dist: diffusers ==0.19.3
Requires-Dist: ftfy ==6.1.1
Requires-Dist: imageio ==2.31.1
Requires-Dist: imageio-ffmpeg ==0.4.8
Requires-Dist: torch ==2.0.1
Requires-Dist: transformers ==4.31.0
Requires-Dist: matplotlib ==3.7.2
Requires-Dist: numpy ==1.25.2
Requires-Dist: scipy ==1.11.1
Provides-Extra: dev
Requires-Dist: black ==23.7.0 ; extra == 'dev'
Requires-Dist: pytest ==7.4.0 ; extra == 'dev'
Requires-Dist: twine >=4.0.2 ; extra == 'dev'
